elysium_api/__init__.py
elysium_api/api.py
elysium_api/clients.py
elysium_api/messages.py
elysium_api/plans.py
elysium_api-1.1.9.dist-info/METADATA
elysium_api-1.1.9.dist-info/WHEEL
elysium_api-1.1.9.dist-info/top_level.txt
elysium_api-1.1.9.dist-info/RECORD
